{
  "1": {
    "ingles": "D",
    "espanhol": "B"
  },
  "46": "E",
  "2": {
    "ingles": "D",
    "espanhol": "A"
  },
  "47": "D",
  "3": {
    "ingles": "D",
    "espanhol": "D"
  },
  "48": "E",
  "4": {
    "ingles": "E",
    "espanhol": "D"
  },
  "49": "C",
  "5": {
    "ingles": "A",
    "espanhol": "C"
  },
  "50": "A",
  "6": "E",
  "51": "D",
  "7": "C",
  "52": "C",
  "8": "D",
  "53": "E",
  "9": "C",
  "54": "E",
  "10": "E",
  "55": "D",
  "11": "B",
  "56": "C",
  "12": "C",
  "57": "A",
  "13": "E",
  "58": "D",
  "14": "C",
  "59": "B",
  "15": "A",
  "60": "D",
  "16": "E",
  "61": "E",
  "17": "C",
  "62": "B",
  "18": "A",
  "63": "B",
  "19": "E",
  "64": "A",
  "20": "B",
  "65": "C",
  "21": "C",
  "66": "D",
  "22": "B",
  "67": "D",
  "23": "C",
  "68": "E",
  "24": "B",
  "69": "C",
  "25": "E",
  "70": "B",
  "26": "B",
  "71": "A",
  "27": "A",
  "72": "D",
  "28": "B",
  "73": "A",
  "29": "A",
  "74": "B",
  "30": "B",
  "75": "B",
  "31": "D",
  "76": "C",
  "32": "E",
  "77": "A",
  "33": "B",
  "78": "B",
  "34": "C",
  "79": "A",
  "35": "E",
  "80": "C",
  "36": "D",
  "81": "E",
  "37": "A",
  "82": "E",
  "38": "B",
  "83": "D",
  "39": "C",
  "84": "D",
  "40": "A",
  "85": "B",
  "41": "B",
  "86": "C",
  "42": "A",
  "87": "B",
  "43": "D",
  "88": "C",
  "44": "D",
  "89": "E",
  "45": "C",
  "90": "A"
}